{"@context":{"geojson":"https:\/\/purl.org\/geojson\/vocab#","Feature":"geojson:Feature","FeatureCollection":"geojson:FeatureCollection","GeometryCollection":"geojson:GeometryCollection","LineString":"geojson:LineString","MultiLineString":"geojson:MultiLineString","MultiPoint":"geojson:MultiPoint","MultiPolygon":"geojson:MultiPolygon","Point":"geojson:Point","Polygon":"geojson:Polygon","bbox":{"@container":"@list","@id":"geojson:bbox"},"coordinates":{"@container":"@list","@id":"geojson:coordinates"},"features":{"@container":"@set","@id":"geojson:features"},"geometry":"geojson:geometry","id":"@id","properties":"geojson:properties","type":"@type","description":"http:\/\/purl.org\/dc\/terms\/description","title":"http:\/\/purl.org\/dc\/terms\/title","label":"http:\/\/schema.org\/name","occupants":{"@reverse":"http:\/\/schema.org\/address"}},"type":"FeatureCollection","features":[{"type":"Feature","geometry":{"type":"Point","coordinates":[4.9013731,52.3693213]},"properties":{"cnt":"15","label":"","adresid":"A102840"}},{"type":"Feature","geometry":{"type":"Point","coordinates":[4.9018954,52.3692669]},"properties":{"cnt":"11","label":"","adresid":"A101782"}},{"type":"Feature","geometry":{"type":"Point","coordinates":[4.9027312,52.3687503]},"properties":{"cnt":"1","label":"","adresid":"A102934"}},{"type":"Feature","geometry":{"type":"Point","coordinates":[4.9047736,52.3681005]},"properties":{"cnt":"6","label":"Sint Anothiesbreestraat (Noordzijde)","adresid":"A102064"}},{"type":"Feature","geometry":{"type":"Point","coordinates":[4.9016461372375,52.369373321533]},"properties":{"cnt":"6","label":"","adresid":"A101762"}},{"type":"Feature","geometry":{"type":"Point","coordinates":[4.9025906,52.3689882]},"properties":{"cnt":"1","label":"Jodenbreestraat 35","adresid":"A101845"}},{"type":"Feature","geometry":{"type":"Point","coordinates":[4.9015622,52.3694095]},"properties":{"cnt":"7","label":"","adresid":"A101757"}},{"type":"Feature","geometry":{"type":"Point","coordinates":[4.9014029,52.3694778]},"properties":{"cnt":"3","label":"","adresid":"A101742"}}]}